{
    "info": {
        "name": "/trsetup",
        "oposite": "/trdisable",
        "permissions": ["Administrator"],
        "category": "Configuration",
        "description": "Setup the temporary channels system in this server.",
        "usage": "/trsetup",
        "examples": null
    },
    "setupSystem": "Temporary channels system activated succesfully!",
    "alreadyActivated": "The temporary channels system is already activated. If you want another intance of temporary channels, get premium: <coming soon>"
}